<root>
  <tile>
    <velocity relX="0" relY="0" vx="0.2854795" vy="-0.1400978" />
    <velocity relX="0.1" relY="0" vx="0.2729557" vy="-0.1919557" />
    <velocity relX="0.2" relY="0" vx="0.2579573" vy="-0.2057087" />
    <velocity relX="0.3" relY="0" vx="0.2422523" vy="-0.2106908" />
    <velocity relX="0.4" relY="0" vx="0.2261896" vy="-0.215193" />
    <velocity relX="0.5" relY="0" vx="0.209957" vy="-0.2151937" />
    <velocity relX="0.6" relY="0" vx="0.1938944" vy="-0.2106919" />
    <velocity relX="0.7" relY="0" vx="0.1781892" vy="-0.2057109" />
    <velocity relX="0.8" relY="0" vx="0.1631906" vy="-0.1919576" />
    <velocity relX="0.9" relY="0" vx="0.1506662" vy="-0.1401089" />
    <velocity relX="0" relY="0.1" vx="0.3911513" vy="-0.127574" />
    <velocity relX="0.1" relY="0.1" vx="0.3739917" vy="-0.1747961" />
    <velocity relX="0.2" relY="0.1" vx="0.3534415" vy="-0.1873197" />
    <velocity relX="0.3" relY="0.1" vx="0.3319232" vy="-0.1918566" />
    <velocity relX="0.4" relY="0.1" vx="0.3099147" vy="-0.1959561" />
    <velocity relX="0.5" relY="0.1" vx="0.2876734" vy="-0.1959568" />
    <velocity relX="0.6" relY="0.1" vx="0.2656647" vy="-0.1918573" />
    <velocity relX="0.7" relY="0.1" vx="0.2441463" vy="-0.1873219" />
    <velocity relX="0.8" relY="0.1" vx="0.2235959" vy="-0.1747978" />
    <velocity relX="0.9" relY="0.1" vx="0.2064357" vy="-0.127584" />
    <velocity relX="0" relY="0.2" vx="0.4191761" vy="-0.1125755" />
    <velocity relX="0.1" relY="0.2" vx="0.400787" vy="-0.154246" />
    <velocity relX="0.2" relY="0.2" vx="0.3787645" vy="-0.1652972" />
    <velocity relX="0.3" relY="0.2" vx="0.3557045" vy="-0.1693007" />
    <velocity relX="0.4" relY="0.2" vx="0.3321192" vy="-0.1729182" />
    <velocity relX="0.5" relY="0.2" vx="0.3082846" vy="-0.1729188" />
    <velocity relX="0.6" relY="0.2" vx="0.2846993" vy="-0.1693015" />
    <velocity relX="0.7" relY="0.2" vx="0.261639" vy="-0.1652989" />
    <velocity relX="0.8" relY="0.2" vx="0.2396162" vy="-0.1542473" />
    <velocity relX="0.9" relY="0.2" vx="0.2212265" vy="-0.1125846" />
    <velocity relX="0" relY="0.3" vx="0.429328" vy="-0.09687042" />
    <velocity relX="0.1" relY="0.3" vx="0.4104937" vy="-0.1327276" />
    <velocity relX="0.2" relY="0.3" vx="0.3879379" vy="-0.1422372" />
    <velocity relX="0.3" relY="0.3" vx="0.3643193" vy="-0.1456823" />
    <velocity relX="0.4" relY="0.3" vx="0.340163" vy="-0.1487949" />
    <velocity relX="0.5" relY="0.3" vx="0.3157508" vy="-0.1487956" />
    <velocity relX="0.6" relY="0.3" vx="0.2915945" vy="-0.1456828" />
    <velocity relX="0.7" relY="0.3" vx="0.2679758" vy="-0.1422386" />
    <velocity relX="0.8" relY="0.3" vx="0.2454197" vy="-0.1327288" />
    <velocity relX="0.9" relY="0.3" vx="0.2265847" vy="-0.09687829" />
    <velocity relX="0" relY="0.4" vx="0.4385026" vy="-0.08080792" />
    <velocity relX="0.1" relY="0.4" vx="0.4192655" vy="-0.110719" />
    <velocity relX="0.2" relY="0.4" vx="0.3962276" vy="-0.1186519" />
    <velocity relX="0.3" relY="0.4" vx="0.3721042" vy="-0.121526" />
    <velocity relX="0.4" relY="0.4" vx="0.3474317" vy="-0.1241221" />
    <velocity relX="0.5" relY="0.4" vx="0.3224983" vy="-0.1241229" />
    <velocity relX="0.6" relY="0.4" vx="0.2978253" vy="-0.1215262" />
    <velocity relX="0.7" relY="0.4" vx="0.2737017" vy="-0.1186531" />
    <velocity relX="0.8" relY="0.4" vx="0.2506635" vy="-0.1107202" />
    <velocity relX="0.9" relY="0.4" vx="0.2314262" vy="-0.08081436" />
    <velocity relX="0" relY="0.5" vx="0.4385037" vy="-0.0645752" />
    <velocity relX="0.1" relY="0.5" vx="0.4192667" vy="-0.08847785" />
    <velocity relX="0.2" relY="0.5" vx="0.3962288" vy="-0.09481716" />
    <velocity relX="0.3" relY="0.5" vx="0.3721058" vy="-0.09711409" />
    <velocity relX="0.4" relY="0.5" vx="0.3474329" vy="-0.09918833" />
    <velocity relX="0.5" relY="0.5" vx="0.322499" vy="-0.09918928" />
    <velocity relX="0.6" relY="0.5" vx="0.2978261" vy="-0.09711432" />
    <velocity relX="0.7" relY="0.5" vx="0.2737029" vy="-0.09481788" />
    <velocity relX="0.8" relY="0.5" vx="0.2506647" vy="-0.08847904" />
    <velocity relX="0.9" relY="0.5" vx="0.2314267" vy="-0.06458044" />
    <velocity relX="0" relY="0.6" vx="0.4293301" vy="-0.04851246" />
    <velocity relX="0.1" relY="0.6" vx="0.4104958" vy="-0.06646919" />
    <velocity relX="0.2" relY="0.6" vx="0.3879395" vy="-0.07123184" />
    <velocity relX="0.3" relY="0.6" vx="0.364321" vy="-0.07295799" />
    <velocity relX="0.4" relY="0.6" vx="0.3401644" vy="-0.07451534" />
    <velocity relX="0.5" relY="0.6" vx="0.3157523" vy="-0.0745163" />
    <velocity relX="0.6" relY="0.6" vx="0.2915959" vy="-0.07295752" />
    <velocity relX="0.7" relY="0.6" vx="0.267977" vy="-0.07123232" />
    <velocity relX="0.8" relY="0.6" vx="0.2454207" vy="-0.06647015" />
    <velocity relX="0.9" relY="0.6" vx="0.2265856" vy="-0.04851651" />
    <velocity relX="0" relY="0.7" vx="0.4191806" vy="-0.03280735" />
    <velocity relX="0.1" relY="0.7" vx="0.4007912" vy="-0.04495049" />
    <velocity relX="0.2" relY="0.7" vx="0.3787687" vy="-0.04817176" />
    <velocity relX="0.3" relY="0.7" vx="0.3557086" vy="-0.04933929" />
    <velocity relX="0.4" relY="0.7" vx="0.3321228" vy="-0.05039191" />
    <velocity relX="0.5" relY="0.7" vx="0.3082881" vy="-0.05039287" />
    <velocity relX="0.6" relY="0.7" vx="0.2847023" vy="-0.04933858" />
    <velocity relX="0.7" relY="0.7" vx="0.2616417" vy="-0.048172" />
    <velocity relX="0.8" relY="0.7" vx="0.239619" vy="-0.04495144" />
    <velocity relX="0.9" relY="0.7" vx="0.2212291" vy="-0.03281021" />
    <velocity relX="0" relY="0.8" vx="0.3911548" vy="-0.01780844" />
    <velocity relX="0.1" relY="0.8" vx="0.3739953" vy="-0.02440023" />
    <velocity relX="0.2" relY="0.8" vx="0.3534448" vy="-0.02614903" />
    <velocity relX="0.3" relY="0.8" vx="0.3319261" vy="-0.02678323" />
    <velocity relX="0.4" relY="0.8" vx="0.3099174" vy="-0.02735376" />
    <velocity relX="0.5" relY="0.8" vx="0.2876763" vy="-0.02735472" />
    <velocity relX="0.6" relY="0.8" vx="0.2656674" vy="-0.02678227" />
    <velocity relX="0.7" relY="0.8" vx="0.2441487" vy="-0.02614927" />
    <velocity relX="0.8" relY="0.8" vx="0.2235982" vy="-0.02440095" />
    <velocity relX="0.9" relY="0.8" vx="0.2064378" vy="-0.01781011" />
    <velocity relX="0" relY="0.9" vx="0.2855024" vy="-0.005284309" />
    <velocity relX="0.1" relY="0.9" vx="0.2729776" vy="-0.007240057" />
    <velocity relX="0.2" relY="0.9" vx="0.257978" vy="-0.007759333" />
    <velocity relX="0.3" relY="0.9" vx="0.2422717" vy="-0.007947922" />
    <velocity relX="0.4" relY="0.9" vx="0.2262077" vy="-0.008116245" />
    <velocity relX="0.5" relY="0.9" vx="0.2099738" vy="-0.008117199" />
    <velocity relX="0.6" relY="0.9" vx="0.1939096" vy="-0.007946968" />
    <velocity relX="0.7" relY="0.9" vx="0.1782033" vy="-0.007759333" />
    <velocity relX="0.8" relY="0.9" vx="0.1632035" vy="-0.007240534" />
    <velocity relX="0.9" relY="0.9" vx="0.1506782" vy="-0.005284786" />
  </tile>
  <tile>
    <velocity relX="0" relY="0" vx="0.2881215" vy="-0.07004891" />
    <velocity relX="0.1" relY="0" vx="0.2818596" vy="-0.09597783" />
    <velocity relX="0.2" relY="0" vx="0.2743604" vy="-0.1028544" />
    <velocity relX="0.3" relY="0" vx="0.2665079" vy="-0.1053454" />
    <velocity relX="0.4" relY="0" vx="0.2584766" vy="-0.1075965" />
    <velocity relX="0.5" relY="0" vx="0.2503602" vy="-0.1075969" />
    <velocity relX="0.6" relY="0" vx="0.2423289" vy="-0.1053459" />
    <velocity relX="0.7" relY="0" vx="0.2344763" vy="-0.1028554" />
    <velocity relX="0.8" relY="0" vx="0.226977" vy="-0.09597886" />
    <velocity relX="0.9" relY="0" vx="0.2207148" vy="-0.07005441" />
    <velocity relX="0" relY="0.1" vx="0.3947712" vy="-0.06378701" />
    <velocity relX="0.1" relY="0.1" vx="0.3861914" vy="-0.08739805" />
    <velocity relX="0.2" relY="0.1" vx="0.3759164" vy="-0.09365982" />
    <velocity relX="0.3" relY="0.1" vx="0.3651571" vy="-0.09592831" />
    <velocity relX="0.4" relY="0.1" vx="0.3541529" vy="-0.097978" />
    <velocity relX="0.5" relY="0.1" vx="0.3430324" vy="-0.09797853" />
    <velocity relX="0.6" relY="0.1" vx="0.332028" vy="-0.09592867" />
    <velocity relX="0.7" relY="0.1" vx="0.3212687" vy="-0.09366083" />
    <velocity relX="0.8" relY="0.1" vx="0.3109936" vy="-0.08739889" />
    <velocity relX="0.9" relY="0.1" vx="0.3024135" vy="-0.06379211" />
    <velocity relX="0" relY="0.2" vx="0.4230554" vy="-0.05628777" />
    <velocity relX="0.1" relY="0.2" vx="0.4138608" vy="-0.07712293" />
    <velocity relX="0.2" relY="0.2" vx="0.4028494" vy="-0.08264852" />
    <velocity relX="0.3" relY="0.2" vx="0.3913196" vy="-0.08465052" />
    <velocity relX="0.4" relY="0.2" vx="0.379527" vy="-0.08645904" />
    <velocity relX="0.5" relY="0.2" vx="0.3676095" vy="-0.08645952" />
    <velocity relX="0.6" relY="0.2" vx="0.3558168" vy="-0.08465052" />
    <velocity relX="0.7" relY="0.2" vx="0.3442868" vy="-0.08264959" />
    <velocity relX="0.8" relY="0.2" vx="0.3332754" vy="-0.07712376" />
    <velocity relX="0.9" relY="0.2" vx="0.3240806" vy="-0.0562923" />
    <velocity relX="0" relY="0.3" vx="0.4333013" vy="-0.04843521" />
    <velocity relX="0.1" relY="0.3" vx="0.4238842" vy="-0.06636381" />
    <velocity relX="0.2" relY="0.3" vx="0.4126062" vy="-0.07111859" />
    <velocity relX="0.3" relY="0.3" vx="0.4007969" vy="-0.07284117" />
    <velocity relX="0.4" relY="0.3" vx="0.3887187" vy="-0.07439733" />
    <velocity relX="0.5" relY="0.3" vx="0.3765128" vy="-0.0743978" />
    <velocity relX="0.6" relY="0.3" vx="0.3644346" vy="-0.07284141" />
    <velocity relX="0.7" relY="0.3" vx="0.3526253" vy="-0.07111931" />
    <velocity relX="0.8" relY="0.3" vx="0.341347" vy="-0.06636453" />
    <velocity relX="0.9" relY="0.3" vx="0.3319296" vy="-0.04843903" />
    <velocity relX="0" relY="0.4" vx="0.4425604" vy="-0.04040408" />
    <velocity relX="0.1" relY="0.4" vx="0.432942" vy="-0.05535936" />
    <velocity relX="0.2" relY="0.4" vx="0.4214232" vy="-0.05932593" />
    <velocity relX="0.3" relY="0.4" vx="0.4093616" vy="-0.060763" />
    <velocity relX="0.4" relY="0.4" vx="0.3970251" vy="-0.06206095" />
    <velocity relX="0.5" relY="0.4" vx="0.3845584" vy="-0.06206155" />
    <velocity relX="0.6" relY="0.4" vx="0.3722218" vy="-0.06076312" />
    <velocity relX="0.7" relY="0.4" vx="0.3601604" vy="-0.05932665" />
    <velocity relX="0.8" relY="0.4" vx="0.3486414" vy="-0.05535984" />
    <velocity relX="0.9" relY="0.4" vx="0.3390224" vy="-0.04040718" />
    <velocity relX="0" relY="0.5" vx="0.4425619" vy="-0.0322876" />
    <velocity relX="0.1" relY="0.5" vx="0.4329433" vy="-0.04423881" />
    <velocity relX="0.2" relY="0.5" vx="0.4214244" vy="-0.04740858" />
    <velocity relX="0.3" relY="0.5" vx="0.4093628" vy="-0.04855728" />
    <velocity relX="0.4" relY="0.5" vx="0.3970265" vy="-0.04959393" />
    <velocity relX="0.5" relY="0.5" vx="0.3845596" vy="-0.04959488" />
    <velocity relX="0.6" relY="0.5" vx="0.3722234" vy="-0.0485568" />
    <velocity relX="0.7" relY="0.5" vx="0.3601613" vy="-0.0474093" />
    <velocity relX="0.8" relY="0.5" vx="0.3486423" vy="-0.04423928" />
    <velocity relX="0.9" relY="0.5" vx="0.3390236" vy="-0.03229046" />
    <velocity relX="0" relY="0.6" vx="0.4333034" vy="-0.02425623" />
    <velocity relX="0.1" relY="0.6" vx="0.4238863" vy="-0.0332346" />
    <velocity relX="0.2" relY="0.6" vx="0.4126081" vy="-0.03561592" />
    <velocity relX="0.3" relY="0.6" vx="0.4007988" vy="-0.03647923" />
    <velocity relX="0.4" relY="0.6" vx="0.3887205" vy="-0.03725719" />
    <velocity relX="0.5" relY="0.6" vx="0.3765144" vy="-0.03725839" />
    <velocity relX="0.6" relY="0.6" vx="0.3644361" vy="-0.03647876" />
    <velocity relX="0.7" relY="0.6" vx="0.3526268" vy="-0.0356164" />
    <velocity relX="0.8" relY="0.6" vx="0.3413486" vy="-0.03323483" />
    <velocity relX="0.9" relY="0.6" vx="0.3319311" vy="-0.02425814" />
    <velocity relX="0" relY="0.7" vx="0.4230599" vy="-0.01640368" />
    <velocity relX="0.1" relY="0.7" vx="0.4138651" vy="-0.02247524" />
    <velocity relX="0.2" relY="0.7" vx="0.4028537" vy="-0.02408576" />
    <velocity relX="0.3" relY="0.7" vx="0.3913238" vy="-0.02466989" />
    <velocity relX="0.4" relY="0.7" vx="0.3795311" vy="-0.0251956" />
    <velocity relX="0.5" relY="0.7" vx="0.3676136" vy="-0.02519679" />
    <velocity relX="0.6" relY="0.7" vx="0.3558207" vy="-0.02466917" />
    <velocity relX="0.7" relY="0.7" vx="0.3442905" vy="-0.02408624" />
    <velocity relX="0.8" relY="0.7" vx="0.3332791" vy="-0.02247572" />
    <velocity relX="0.9" relY="0.7" vx="0.324084" vy="-0.01640463" />
    <velocity relX="0" relY="0.8" vx="0.3947749" vy="-0.008904219" />
    <velocity relX="0.1" relY="0.8" vx="0.3861952" vy="-0.01220012" />
    <velocity relX="0.2" relY="0.8" vx="0.3759201" vy="-0.0130744" />
    <velocity relX="0.3" relY="0.8" vx="0.3651607" vy="-0.01339197" />
    <velocity relX="0.4" relY="0.8" vx="0.354156" vy="-0.01367617" />
    <velocity relX="0.5" relY="0.8" vx="0.3430355" vy="-0.01367784" />
    <velocity relX="0.6" relY="0.8" vx="0.3320313" vy="-0.01339102" />
    <velocity relX="0.7" relY="0.8" vx="0.3212717" vy="-0.01307464" />
    <velocity relX="0.8" relY="0.8" vx="0.3109965" vy="-0.01220059" />
    <velocity relX="0.9" relY="0.8" vx="0.3024163" vy="-0.008904934" />
    <velocity relX="0" relY="0.9" vx="0.2881446" vy="-0.002642155" />
    <velocity relX="0.1" relY="0.9" vx="0.281882" vy="-0.003619909" />
    <velocity relX="0.2" relY="0.9" vx="0.2743821" vy="-0.003879547" />
    <velocity relX="0.3" relY="0.9" vx="0.2665291" vy="-0.003974438" />
    <velocity relX="0.4" relY="0.9" vx="0.2584972" vy="-0.004057646" />
    <velocity relX="0.5" relY="0.9" vx="0.2503805" vy="-0.004058838" />
    <velocity relX="0.6" relY="0.9" vx="0.2423482" vy="-0.003973484" />
    <velocity relX="0.7" relY="0.9" vx="0.2344952" vy="-0.003879547" />
    <velocity relX="0.8" relY="0.9" vx="0.226995" vy="-0.003620386" />
    <velocity relX="0.9" relY="0.9" vx="0.2207325" vy="-0.002642393" />
  </tile>
  <tile>
    <velocity relX="0" relY="0" vx="0.2907635" vy="0" />
    <velocity relX="0.1" relY="0" vx="0.2907635" vy="1.490116E-08" />
    <velocity relX="0.2" relY="0" vx="0.2907635" vy="0" />
    <velocity relX="0.3" relY="0" vx="0.2907635" vy="-4.470348E-08" />
    <velocity relX="0.4" relY="0" vx="0.2907635" vy="4.470348E-08" />
    <velocity relX="0.5" relY="0" vx="0.2907635" vy="-1.490116E-08" />
    <velocity relX="0.6" relY="0" vx="0.2907635" vy="0" />
    <velocity relX="0.7" relY="0" vx="0.2907635" vy="0" />
    <velocity relX="0.8" relY="0" vx="0.2907635" vy="0" />
    <velocity relX="0.9" relY="0" vx="0.2907635" vy="0" />
    <velocity relX="0" relY="0.1" vx="0.3983912" vy="0" />
    <velocity relX="0.1" relY="0.1" vx="0.3983911" vy="2.980232E-08" />
    <velocity relX="0.2" relY="0.1" vx="0.3983912" vy="0" />
    <velocity relX="0.3" relY="0.1" vx="0.3983912" vy="-8.940697E-08" />
    <velocity relX="0.4" relY="0.1" vx="0.3983912" vy="8.940697E-08" />
    <velocity relX="0.5" relY="0.1" vx="0.3983911" vy="-2.980232E-08" />
    <velocity relX="0.6" relY="0.1" vx="0.3983912" vy="0" />
    <velocity relX="0.7" relY="0.1" vx="0.3983912" vy="0" />
    <velocity relX="0.8" relY="0.1" vx="0.3983912" vy="0" />
    <velocity relX="0.9" relY="0.1" vx="0.3983912" vy="0" />
    <velocity relX="0" relY="0.2" vx="0.4269347" vy="0" />
    <velocity relX="0.1" relY="0.2" vx="0.4269346" vy="1.192093E-07" />
    <velocity relX="0.2" relY="0.2" vx="0.4269345" vy="0" />
    <velocity relX="0.3" relY="0.2" vx="0.4269347" vy="-2.384186E-07" />
    <velocity relX="0.4" relY="0.2" vx="0.4269347" vy="1.788139E-07" />
    <velocity relX="0.5" relY="0.2" vx="0.4269347" vy="-5.960464E-08" />
    <velocity relX="0.6" relY="0.2" vx="0.4269347" vy="0" />
    <velocity relX="0.7" relY="0.2" vx="0.4269347" vy="0" />
    <velocity relX="0.8" relY="0.2" vx="0.4269347" vy="0" />
    <velocity relX="0.9" relY="0.2" vx="0.4269347" vy="0" />
    <velocity relX="0" relY="0.3" vx="0.4372745" vy="0" />
    <velocity relX="0.1" relY="0.3" vx="0.4372746" vy="2.384186E-07" />
    <velocity relX="0.2" relY="0.3" vx="0.4372746" vy="0" />
    <velocity relX="0.3" relY="0.3" vx="0.4372745" vy="-3.576279E-07" />
    <velocity relX="0.4" relY="0.3" vx="0.4372745" vy="2.384186E-07" />
    <velocity relX="0.5" relY="0.3" vx="0.4372745" vy="-1.192093E-07" />
    <velocity relX="0.6" relY="0.3" vx="0.4372745" vy="0" />
    <velocity relX="0.7" relY="0.3" vx="0.4372745" vy="0" />
    <velocity relX="0.8" relY="0.3" vx="0.4372745" vy="0" />
    <velocity relX="0.9" relY="0.3" vx="0.4372745" vy="0" />
    <velocity relX="0" relY="0.4" vx="0.4466187" vy="0" />
    <velocity relX="0.1" relY="0.4" vx="0.4466186" vy="0" />
    <velocity relX="0.2" relY="0.4" vx="0.4466187" vy="0" />
    <velocity relX="0.3" relY="0.4" vx="0.4466188" vy="-2.384186E-07" />
    <velocity relX="0.4" relY="0.4" vx="0.4466188" vy="2.384186E-07" />
    <velocity relX="0.5" relY="0.4" vx="0.4466186" vy="0" />
    <velocity relX="0.6" relY="0.4" vx="0.4466187" vy="0" />
    <velocity relX="0.7" relY="0.4" vx="0.4466187" vy="0" />
    <velocity relX="0.8" relY="0.4" vx="0.4466187" vy="0" />
    <velocity relX="0.9" relY="0.4" vx="0.4466187" vy="0" />
    <velocity relX="0" relY="0.5" vx="0.4466201" vy="0" />
    <velocity relX="0.1" relY="0.5" vx="0.44662" vy="2.384186E-07" />
    <velocity relX="0.2" relY="0.5" vx="0.4466197" vy="0" />
    <velocity relX="0.3" relY="0.5" vx="0.4466197" vy="-4.768372E-07" />
    <velocity relX="0.4" relY="0.5" vx="0.44662" vy="4.768372E-07" />
    <velocity relX="0.5" relY="0.5" vx="0.44662" vy="-2.384186E-07" />
    <velocity relX="0.6" relY="0.5" vx="0.4466201" vy="0" />
    <velocity relX="0.7" relY="0.5" vx="0.4466201" vy="0" />
    <velocity relX="0.8" relY="0.5" vx="0.4466201" vy="0" />
    <velocity relX="0.9" relY="0.5" vx="0.4466201" vy="0" />
    <velocity relX="0" relY="0.6" vx="0.4372766" vy="0" />
    <velocity relX="0.1" relY="0.6" vx="0.4372766" vy="4.768372E-07" />
    <velocity relX="0.2" relY="0.6" vx="0.4372766" vy="0" />
    <velocity relX="0.3" relY="0.6" vx="0.4372768" vy="-9.536743E-07" />
    <velocity relX="0.4" relY="0.6" vx="0.4372766" vy="4.768372E-07" />
    <velocity relX="0.5" relY="0.6" vx="0.4372768" vy="0" />
    <velocity relX="0.6" relY="0.6" vx="0.4372766" vy="0" />
    <velocity relX="0.7" relY="0.6" vx="0.4372766" vy="0" />
    <velocity relX="0.8" relY="0.6" vx="0.4372766" vy="0" />
    <velocity relX="0.9" relY="0.6" vx="0.4372766" vy="0" />
    <velocity relX="0" relY="0.7" vx="0.4269392" vy="0" />
    <velocity relX="0.1" relY="0.7" vx="0.4269392" vy="4.768372E-07" />
    <velocity relX="0.2" relY="0.7" vx="0.4269392" vy="0" />
    <velocity relX="0.3" relY="0.7" vx="0.4269392" vy="-9.536743E-07" />
    <velocity relX="0.4" relY="0.7" vx="0.4269395" vy="4.768372E-07" />
    <velocity relX="0.5" relY="0.7" vx="0.426939" vy="0" />
    <velocity relX="0.6" relY="0.7" vx="0.4269392" vy="0" />
    <velocity relX="0.7" relY="0.7" vx="0.4269392" vy="0" />
    <velocity relX="0.8" relY="0.7" vx="0.4269392" vy="0" />
    <velocity relX="0.9" relY="0.7" vx="0.4269392" vy="0" />
    <velocity relX="0" relY="0.8" vx="0.3983948" vy="0" />
    <velocity relX="0.1" relY="0.8" vx="0.3983948" vy="4.768372E-07" />
    <velocity relX="0.2" relY="0.8" vx="0.3983948" vy="0" />
    <velocity relX="0.3" relY="0.8" vx="0.3983948" vy="-9.536743E-07" />
    <velocity relX="0.4" relY="0.8" vx="0.3983946" vy="9.536743E-07" />
    <velocity relX="0.5" relY="0.8" vx="0.3983948" vy="-4.768372E-07" />
    <velocity relX="0.6" relY="0.8" vx="0.3983948" vy="0" />
    <velocity relX="0.7" relY="0.8" vx="0.3983948" vy="0" />
    <velocity relX="0.8" relY="0.8" vx="0.3983948" vy="0" />
    <velocity relX="0.9" relY="0.8" vx="0.3983948" vy="0" />
    <velocity relX="0" relY="0.9" vx="0.2907867" vy="0" />
    <velocity relX="0.1" relY="0.9" vx="0.2907867" vy="4.768372E-07" />
    <velocity relX="0.2" relY="0.9" vx="0.2907867" vy="0" />
    <velocity relX="0.3" relY="0.9" vx="0.2907867" vy="-9.536743E-07" />
    <velocity relX="0.4" relY="0.9" vx="0.2907867" vy="9.536743E-07" />
    <velocity relX="0.5" relY="0.9" vx="0.290787" vy="-4.768372E-07" />
    <velocity relX="0.6" relY="0.9" vx="0.2907867" vy="0" />
    <velocity relX="0.7" relY="0.9" vx="0.2907867" vy="0" />
    <velocity relX="0.8" relY="0.9" vx="0.2907867" vy="0" />
    <velocity relX="0.9" relY="0.9" vx="0.2907867" vy="0" />
  </tile>
</root>